{
    "version": "1.0.0",
    "description": "Download highest quality YouTube video + audio List using yt-dlp and ffmpeg.",
    "homepage": "https://github.com/huxiaoning/ytbest",
    "license": "MIT",
    "depends": [
        "yt-dlp",
        "ffmpeg",
        "yt-dlp-ChromeCookieUnlock"
    ],
    "url": "https://raw.githubusercontent.com/huxiaoning/ytbest/refs/heads/main/ytlist.ps1",
    "hash": "sha256:0a661c0c995b7f7712eaa13c01e763f7630a320e3f1e5b9ce3fb821e6d1f0c2f",
    "bin": "ytlist.ps1",
    "notes": [
        "Usage:",
        "  ytlist <YouTube_List_URL>"
    ]
}
